fortunekh/__init__.py
fortunekh/fortuneo.py
fortunekh/py.typed
fortunekh-0.2.0.dist-info/entry_points.txt
fortunekh-0.2.0.dist-info/WHEEL
fortunekh-0.2.0.dist-info/METADATA
fortunekh-0.2.0.dist-info/RECORD
